Metadata-Version: 1.0
Name: trackclip
Version: 0.0.4
Summary: Annotate videos by adding an automatically moving frame with a label.
Home-page: https://github.com/protecto/trackclip
Author: protecto
Author-email: UNKNOWN
License: MIT License
Platform: UNKNOWN
